LICENSE
MANIFEST.in
README.md
requirements.txt
setup.py
django_logging_context/__init__.py
django_logging_context/apps.py
django_logging_context/logging.py
django_logging_context/middlewares.py
django_logging_context/signals.py
django_logging_context/tools.py
django_logging_context/wsgi.py
django_logging_context.egg-info/PKG-INFO
django_logging_context.egg-info/SOURCES.txt
django_logging_context.egg-info/dependency_links.txt
django_logging_context.egg-info/not-zip-safe
django_logging_context.egg-info/requires.txt
django_logging_context.egg-info/top_level.txt